rigeo/__init__.py
rigeo/closest.py
rigeo/constraint.py
rigeo/inertial.py
rigeo/moment.py
rigeo/polydd.py
rigeo/random.py
rigeo/rigidbody.py
rigeo/spatial.py
rigeo/util.py
rigeo/shape/__init__.py
rigeo/shape/base.py
rigeo/shape/box.py
rigeo/shape/capsule.py
rigeo/shape/cylinder.py
rigeo/shape/ellipsoid.py
rigeo/shape/poly.py
rigeo/unused/geodesic.py
rigeo/unused/identify.py
rigeo/unused/multibody.py
rigeo/unused/polydd_pycddlib3.py
rigeo-0.2.0.dist-info/METADATA
rigeo-0.2.0.dist-info/WHEEL
rigeo-0.2.0.dist-info/licenses/LICENSE
rigeo-0.2.0.dist-info/RECORD
