Metadata-Version: 2.4
Name: rigeo
Version: 0.2.0
Summary: Rigid body geometry and inertial parameters.
Author-email: Adam Heins <mail@adamheins.com>
License: MIT
License-File: LICENSE
Requires-Python: >=3.8
Requires-Dist: cvxpy[mosek]!=1.5.0,!=1.5.1,!=1.5.2,!=1.5.3,!=1.5.4,>=1.4.2
Requires-Dist: numpy>=1.23.0
Requires-Dist: pycddlib<3.0.0,>=2.1.6
Requires-Dist: scipy>=1.10.0
Requires-Dist: tqdm>=4.67.1
